pyawx/__init__.py
pyawx/auth.py
pyawx/client.py
pyawx/http.py
pyawx/models/__init__.py
pyawx/models/enums.py
pyawx/models/job_template.py
pyawx/models/workflow_job_template.py
pyawx/resources/__init__.py
pyawx/resources/adapter.py
pyawx/resources/job_template.py
pyawx/resources/workflow_job_template.py
pyawx-0.1.3.dist-info/METADATA
pyawx-0.1.3.dist-info/WHEEL
pyawx-0.1.3.dist-info/licenses/LICENSE
pyawx-0.1.3.dist-info/RECORD
