Metadata-Version: 2.4
Name: pyawx
Version: 0.1.3
Summary: Python client for managing AWX automation platform
Author: srlasagne
License-File: LICENSE
Classifier: Development Status :: 3 - Alpha
Requires-Python: >=3.13
Requires-Dist: pydantic>=2.10.6
Requires-Dist: requests>=2.32.3
